arkitekt_next/__init__.py
arkitekt_next/builders.py
arkitekt_next/constants.py
arkitekt_next/init_registry.py
arkitekt_next/inspect.py
arkitekt_next/node_id.py
arkitekt_next/protocols.py
arkitekt_next/py.typed
arkitekt_next/service_registry.py
arkitekt_next/tqdm.py
arkitekt_next/utils.py
arkitekt_next/app/__init__.py
arkitekt_next/app/app.py
arkitekt_next/app/fakts.py
arkitekt_next/cli/__init__.py
arkitekt_next/cli/constants.py
arkitekt_next/cli/errors.py
arkitekt_next/cli/inspect.py
arkitekt_next/cli/io.py
arkitekt_next/cli/main.py
arkitekt_next/cli/options.py
arkitekt_next/cli/texts.py
arkitekt_next/cli/types.py
arkitekt_next/cli/ui.py
arkitekt_next/cli/utils.py
arkitekt_next/cli/validators.py
arkitekt_next/cli/vars.py
arkitekt_next/cli/commands/call/__init__.py
arkitekt_next/cli/commands/call/local.py
arkitekt_next/cli/commands/call/main.py
arkitekt_next/cli/commands/call/remote.py
arkitekt_next/cli/commands/gen/__init__.py
arkitekt_next/cli/commands/gen/compile.py
arkitekt_next/cli/commands/gen/init.py
arkitekt_next/cli/commands/gen/main.py
arkitekt_next/cli/commands/gen/watch.py
arkitekt_next/cli/commands/init/__init__.py
arkitekt_next/cli/commands/init/main.py
arkitekt_next/cli/commands/inspect/__init__.py
arkitekt_next/cli/commands/inspect/implementations.py
arkitekt_next/cli/commands/inspect/main.py
arkitekt_next/cli/commands/inspect/requirements.py
arkitekt_next/cli/commands/inspect/variables.py
arkitekt_next/cli/commands/kabinet/__init__.py
arkitekt_next/cli/commands/kabinet/build.py
arkitekt_next/cli/commands/kabinet/init.py
arkitekt_next/cli/commands/kabinet/io.py
arkitekt_next/cli/commands/kabinet/main.py
arkitekt_next/cli/commands/kabinet/publish.py
arkitekt_next/cli/commands/kabinet/stage.py
arkitekt_next/cli/commands/kabinet/types.py
arkitekt_next/cli/commands/kabinet/utils.py
arkitekt_next/cli/commands/kabinet/validate.py
arkitekt_next/cli/commands/manifest/__init__.py
arkitekt_next/cli/commands/manifest/inspect.py
arkitekt_next-0.31.1.dist-info/METADATA
arkitekt_next-0.31.1.dist-info/WHEEL
arkitekt_next-0.31.1.dist-info/entry_points.txt
arkitekt_next-0.31.1.dist-info/licenses/LICENSE
arkitekt_next-0.31.1.dist-info/RECORD
