Metadata-Version: 2.4
Name: arkitekt-next
Version: 0.31.1
Summary: client for the arkitekt_next platform
Author-email: jhnnsrs <jhnnsrs@gmail.com>
License-Expression: MIT
License-File: LICENSE
Requires-Python: <4,>=3.11
Requires-Dist: click>=8.2.0
Requires-Dist: dokker>=2.3.0
Requires-Dist: fakts-next>=2.4.0
Requires-Dist: kabinet>=0.9.0
Requires-Dist: koil>=2.0.6
Requires-Dist: platformdirs>=4.5.0
Requires-Dist: rath>=3.7.0
Requires-Dist: rekuest-next>=0.18.3
Requires-Dist: rich-click>=1.8.8
Requires-Dist: semver>=3.0.4
Requires-Dist: turms>=0.10.1
Requires-Dist: watchfiles>=1.0.5
Provides-Extra: all
Requires-Dist: fluss-next>=0.2.0; extra == 'all'
Requires-Dist: kabinet>=0.6.0; extra == 'all'
Requires-Dist: mikro-next>=0.7.2; extra == 'all'
Requires-Dist: reaktion-next>=0.2.0; extra == 'all'
Requires-Dist: rekuest-next>=0.7; extra == 'all'
Requires-Dist: rich-click>=1.6.1; extra == 'all'
Requires-Dist: semver>=3.0.1; extra == 'all'
Requires-Dist: turms>=0.9; extra == 'all'
Requires-Dist: unlok-next>=1.1.1; extra == 'all'
Requires-Dist: watchfiles>=0.18.1; extra == 'all'
Provides-Extra: alpaka
Requires-Dist: alpaka>=0.2.0; extra == 'alpaka'
Provides-Extra: blok
Requires-Dist: blok>=0.1.0; extra == 'blok'
Provides-Extra: cli
Requires-Dist: turms>=0.9.0; extra == 'cli'
Provides-Extra: elektro
Requires-Dist: elektro>=0.5.0; extra == 'elektro'
Provides-Extra: extended
Requires-Dist: alpaka>=0.2.0; extra == 'extended'
Requires-Dist: kraph>=0.2.0; extra == 'extended'
Provides-Extra: fluss
Requires-Dist: fluss-next>=0.2.0; extra == 'fluss'
Provides-Extra: kabinet
Requires-Dist: kabinet>=0.6.0; extra == 'kabinet'
Provides-Extra: kraph
Requires-Dist: kraph>=0.2.0; extra == 'kraph'
Provides-Extra: lovekit
Requires-Dist: lovekit>=0.2.0; extra == 'lovekit'
Provides-Extra: mikro
Requires-Dist: mikro-next>=0.7.2; extra == 'mikro'
Provides-Extra: reaktion
Requires-Dist: reaktion-next>=0.2.0; extra == 'reaktion'
Provides-Extra: unlok
Requires-Dist: unlok-next>=1.1.1; extra == 'unlok'
